upkie/__init__.py
upkie/exceptions.py
upkie/logging.py
upkie/config/__init__.py
upkie/config/bullet_config.py
upkie/config/robot_config.py
upkie/config/spine_config.py
upkie/config/user_config.py
upkie/controllers/__init__.py
upkie/controllers/mpc_balancer/__init__.py
upkie/controllers/mpc_balancer/mpc_balancer.py
upkie/controllers/mpc_balancer/proxqp_workspace.py
upkie/envs/__init__.py
upkie/envs/entry_points.py
upkie/envs/testing.py
upkie/envs/upkie_env.py
upkie/envs/upkie_pendulum.py
upkie/envs/upkie_servos.py
upkie/envs/backends/__init__.py
upkie/envs/backends/backend.py
upkie/envs/backends/genesis_backend.py
upkie/envs/backends/mock_backend.py
upkie/envs/backends/pybullet_backend.py
upkie/envs/backends/spine_backend.py
upkie/envs/backends/spine/__init__.py
upkie/envs/backends/spine/request.py
upkie/envs/backends/spine/serialize.py
upkie/envs/backends/spine/spine_interface.py
upkie/envs/backends/spine/wait_for_shared_memory.py
upkie/envs/wrappers/__init__.py
upkie/envs/wrappers/add_action_to_observation.py
upkie/envs/wrappers/add_lag_to_action.py
upkie/envs/wrappers/differentiate_action.py
upkie/envs/wrappers/noisify_action.py
upkie/envs/wrappers/noisify_observation.py
upkie/envs/wrappers/random_push.py
upkie/model/__init__.py
upkie/model/joint.py
upkie/model/joint_limit.py
upkie/model/model.py
upkie/utils/__init__.py
upkie/utils/clamp.py
upkie/utils/filters.py
upkie/utils/joystick.py
upkie/utils/nested_update.py
upkie/utils/raspi.py
upkie/utils/robot_state.py
upkie/utils/robot_state_randomization.py
upkie/utils/rotations.py
upkie-9.0.1.dist-info/licenses/LICENSE
upkie-9.0.1.dist-info/WHEEL
upkie-9.0.1.dist-info/METADATA
upkie-9.0.1.dist-info/RECORD
