Metadata-Version: 2.4
Name: upkie
Version: 9.0.1
Summary: Python module to control Upkie wheeled bipeds.
Keywords: wheeled,biped,robot,balance,motion,control,robotics
Author-email: Stéphane Caron <stephane.caron@normalesup.org>
Maintainer-email: Stéphane Caron <stephane.caron@normalesup.org>
Requires-Python: >=3.9
Classifier: Development Status :: 4 - Beta
Classifier: Framework :: Robot Framework :: Library
Classifier: Intended Audience :: Developers
Classifier: Intended Audience :: Science/Research
Classifier: License :: OSI Approved :: Apache Software License
Classifier: Operating System :: OS Independent
Classifier: Programming Language :: Python :: 3.9
Classifier: Programming Language :: Python :: 3.10
Classifier: Programming Language :: Python :: 3.11
Classifier: Programming Language :: Python :: 3.12
Classifier: Topic :: Scientific/Engineering
License-File: LICENSE
Requires-Dist: gymnasium >= 1.0.0
Requires-Dist: loop-rate-limiters >= 1.2.0
Requires-Dist: msgpack >= 1.0.2
Requires-Dist: numpy >= 1.24.3
Requires-Dist: pyyaml >=5.3.1
Requires-Dist: scipy >= 1.10.0
Requires-Dist: upkie_description >= 2.1.0
Project-URL: Changelog, https://github.com/upkie/upkie/blob/main/CHANGELOG.md
Project-URL: Documentation, https://upkie.github.io/upkie/
Project-URL: Homepage, https://hackaday.io/project/185729-upkie-wheeled-biped-robots
Project-URL: Source, https://github.com/upkie/upkie
Project-URL: Tracker, https://github.com/upkie/upkie/issues
